czsc/__init__.py
czsc/aphorism.py
czsc/core.py
czsc/eda.py
czsc/envs.py
czsc/mock.py
czsc/strategies.py
czsc/connectors/__init__.py
czsc/connectors/ccxt_connector.py
czsc/connectors/cooperation.py
czsc/connectors/jq_connector.py
czsc/connectors/research.py
czsc/connectors/tq_connector.py
czsc/connectors/ts_connector.py
czsc/features/__init__.py
czsc/features/ret.py
czsc/features/utils.py
czsc/features/vpf.py
czsc/fsa/__init__.py
czsc/fsa/base.py
czsc/fsa/bi_table.py
czsc/fsa/im.py
czsc/fsa/push_strategy_latest.py
czsc/fsa/spreed_sheets.py
czsc/py/__init__.py
czsc/py/analyze.py
czsc/py/bar_generator.py
czsc/py/calendar.py
czsc/py/enum.py
czsc/py/objects.py
czsc/py/weight_backtest.py
czsc/sensors/__init__.py
czsc/sensors/cta.py
czsc/sensors/event.py
czsc/sensors/feature.py
czsc/sensors/utils.py
czsc/signals/__init__.py
czsc/signals/ang.py
czsc/signals/bar.py
czsc/signals/byi.py
czsc/signals/coo.py
czsc/signals/cxt.py
czsc/signals/jcc.py
czsc/signals/pos.py
czsc/signals/tas.py
czsc/signals/vol.py
czsc/signals/xls.py
czsc/signals/zdy.py
czsc/svc/__init__.py
czsc/svc/backtest.py
czsc/svc/base.py
czsc/svc/correlation.py
czsc/svc/factor.py
czsc/svc/forms.py
czsc/svc/price_analysis.py
czsc/svc/returns.py
czsc/svc/statistics.py
czsc/svc/strategy.py
czsc/svc/utils.py
czsc/svc/weights.py
czsc/traders/__init__.py
czsc/traders/base.py
czsc/traders/cwc.py
czsc/traders/dummy.py
czsc/traders/optimize.py
czsc/traders/performance.py
czsc/traders/rwc.py
czsc/traders/sig_parse.py
czsc/traders/weight_backtest.py
czsc/utils/__init__.py
czsc/utils/backtest_report.py
czsc/utils/bi_info.py
czsc/utils/cache.py
czsc/utils/corr.py
czsc/utils/cross.py
czsc/utils/data_client.py
czsc/utils/echarts_plot.py
czsc/utils/events.py
czsc/utils/features.py
czsc/utils/fernet.py
czsc/utils/html_report_builder.py
czsc/utils/index_composition.py
czsc/utils/io.py
czsc/utils/kline_quality.py
czsc/utils/log.py
czsc/utils/mark_czsc_status.py
czsc/utils/oss.py
czsc/utils/plot_backtest.py
czsc-0.10.9.dist-info/METADATA
czsc-0.10.9.dist-info/WHEEL
czsc-0.10.9.dist-info/licenses/LICENSE
czsc-0.10.9.dist-info/RECORD
