Metadata-Version: 2.4
Name: czsc
Version: 0.10.9
Summary: 缠中说禅技术分析工具
Project-URL: Homepage, https://github.com/waditu/czsc
Project-URL: Repository, https://github.com/waditu/czsc
Author-email: zengbin93 <zeng_bin8888@163.com>
License-Expression: Apache-2.0
License-File: LICENSE
Keywords: A股,QUANT,技术分析,期货,程序化交易,缠中说禅,缠论,量化
Classifier: License :: OSI Approved :: Apache Software License
Classifier: Programming Language :: Python :: 3.10
Classifier: Programming Language :: Python :: 3.11
Classifier: Programming Language :: Python :: 3.12
Classifier: Programming Language :: Python :: 3.13
Requires-Python: >=3.10
Requires-Dist: clickhouse-connect
Requires-Dist: cryptography
Requires-Dist: deprecated
Requires-Dist: dill
Requires-Dist: fonttools>=4.61.0
Requires-Dist: lightweight-charts
Requires-Dist: loguru
Requires-Dist: matplotlib
Requires-Dist: numpy
Requires-Dist: openpyxl
Requires-Dist: oss2
Requires-Dist: pandas>=1.0.0
Requires-Dist: parse
Requires-Dist: plotly
Requires-Dist: pyarrow
Requires-Dist: pyecharts>=1.9.1
Requires-Dist: pytz
Requires-Dist: redis
Requires-Dist: requests-toolbelt
Requires-Dist: requests>=2.24.0
Requires-Dist: rs-czsc>=0.1.17.post251110
Requires-Dist: scikit-learn
Requires-Dist: scipy
Requires-Dist: seaborn
Requires-Dist: statsmodels
Requires-Dist: streamlit
Requires-Dist: ta-lib>=0.6
Requires-Dist: tenacity
Requires-Dist: tqdm>=4.66.4
Provides-Extra: all
Requires-Dist: black; extra == 'all'
Requires-Dist: build; extra == 'all'
Requires-Dist: flake8; extra == 'all'
Requires-Dist: ipython; extra == 'all'
Requires-Dist: isort; extra == 'all'
Requires-Dist: jupyter; extra == 'all'
Requires-Dist: pytest-cov>=4.0.0; extra == 'all'
Requires-Dist: pytest>=7.0.0; extra == 'all'
Requires-Dist: twine; extra == 'all'
Provides-Extra: dev
Requires-Dist: black; extra == 'dev'
Requires-Dist: flake8; extra == 'dev'
Requires-Dist: ipython; extra == 'dev'
Requires-Dist: isort; extra == 'dev'
Requires-Dist: jupyter; extra == 'dev'
Provides-Extra: release
Requires-Dist: build; extra == 'release'
Requires-Dist: twine; extra == 'release'
Provides-Extra: test
Requires-Dist: pytest-cov>=4.0.0; extra == 'test'
Requires-Dist: pytest>=7.0.0; extra == 'test'
